bitint.py
bitint-0.1.4.dist-info/LICENSE
bitint-0.1.4.dist-info/METADATA
bitint-0.1.4.dist-info/WHEEL
bitint-0.1.4.dist-info/top_level.txt
bitint-0.1.4.dist-info/RECORD
