Metadata-Version: 2.1
Name: bitint
Version: 0.1.4
Summary: Pure Python implementation of extended integer with named bits.
Author-email: Robin Gottfried <bitint@kebet.cz>
License: MIT License
Project-URL: repository, https://github.com/czervenka/bit-int.git
Project-URL: homepage, https://github.com/czervenka/bit-int
Keywords: bit,int,set,flags,namedtuple
Requires-Python: >=3.8
License-File: LICENSE
